skabelon/__init__.py
skabelon/helper.py
skabelon/loader.py
skabelon/template.py
skabelon/filter/__init__.py
skabelon/filter/common.py
skabelon/filter/latex.py
skabelon/filter/markdown.py
skabelon-1.1.0.dist-info/licenses/LICENSE
tests/dummy/__init__.py
tests/dummy/filters.py
venv/bin/activate_this.py
skabelon-1.1.0.dist-info/METADATA
skabelon-1.1.0.dist-info/WHEEL
skabelon-1.1.0.dist-info/top_level.txt
skabelon-1.1.0.dist-info/RECORD
