Metadata-Version: 2.4
Name: skabelon
Version: 1.1.0
Summary: Create complex document templates using Jinja2
Author-email: rmk2 <ryko@rmk2.org>
License-Expression: Apache-2.0
Project-URL: Repository, https://gitlab.com/rmk2/skabelon
Requires-Python: >=3.13
License-File: LICENSE
Requires-Dist: jinja2~=3.1
Requires-Dist: pyyaml~=6.0
Dynamic: license-file
